gifmak3r/__init__.py
gifmak3r/generator.py
gifmak3r/gif_template.py
gifmak3r/fonts/__init__.py
gifmak3r/fonts/impact.ttf
gifmak3r-1.0.2.dist-info/LICENSE
gifmak3r-1.0.2.dist-info/METADATA
gifmak3r-1.0.2.dist-info/WHEEL
gifmak3r-1.0.2.dist-info/top_level.txt
gifmak3r-1.0.2.dist-info/RECORD
