Metadata-Version: 2.1
Name: gifmak3r
Version: 1.0.2
Summary: A gif generator in Python that creates gifs in user-specified formats
Home-page: https://github.com/frykher/gif-mak3r
Author: Fahim Hussain
Author-email: fahimhussain21@gmail.com
License: UNKNOWN
Project-URL: Bug Tracker, https://github.com/frykher/gif-mak3r/issues
Platform: UNKNOWN
Classifier: Programming Language :: Python :: 3
Classifier: License :: OSI Approved :: MIT License
Classifier: Operating System :: OS Independent
Requires-Python: >=3.6
Requires-Dist: Pillow
